trimgmi/__init__.py
trimgmi/command.py
trimgmi/convert.py
trimgmi/sample.py
trimgmi-0.3.0.dist-info/COPYING
trimgmi-0.3.0.dist-info/METADATA
trimgmi-0.3.0.dist-info/WHEEL
trimgmi-0.3.0.dist-info/entry_points.txt
trimgmi-0.3.0.dist-info/top_level.txt
trimgmi-0.3.0.dist-info/RECORD
