Metadata-Version: 2.1
Name: trimgmi
Version: 0.3.0
Summary: Opinionated parsing of gemtext.
Home-page: https://gitlab.com/lofidevops/trimgmi
Author: David Seaward
Author-email: david@librem.one
License: GPL-3.0-or-later
Platform: UNKNOWN
Classifier: Environment :: Console
Classifier: Intended Audience :: Developers
Classifier: License :: OSI Approved :: GNU General Public License v3 or later (GPLv3+)
Classifier: Programming Language :: Python :: 3
Classifier: Programming Language :: Python :: 3.9
Classifier: Topic :: Text Processing :: Markup
